LICENSE
MANIFEST.in
README.md
pyproject.toml
setup.cfg
setup.py
docassemble.LAWVNameChangeClinic.egg-info/PKG-INFO
docassemble.LAWVNameChangeClinic.egg-info/SOURCES.txt
docassemble.LAWVNameChangeClinic.egg-info/dependency_links.txt
docassemble.LAWVNameChangeClinic.egg-info/not-zip-safe
docassemble.LAWVNameChangeClinic.egg-info/requires.txt
docassemble.LAWVNameChangeClinic.egg-info/top_level.txt
docassemble/LAWVNameChangeClinic/__init__.py
docassemble/LAWVNameChangeClinic/data/questions/name_change_clinic.yml
docassemble/LAWVNameChangeClinic/data/sources/README.md
docassemble/LAWVNameChangeClinic/data/static/README.md
docassemble/LAWVNameChangeClinic/data/templates/README.md
docassemble/LAWVNameChangeClinic/data/templates/name_change_instructions.pdf
docassemble/LAWVNameChangeClinic/data/templates/name_change_order.docx
docassemble/LAWVNameChangeClinic/data/templates/name_change_order_filing_petition.docx
docassemble/LAWVNameChangeClinic/data/templates/name_change_order_of_publication.docx
docassemble/LAWVNameChangeClinic/data/templates/name_change_petition_adult.docx