Metadata-Version: 2.4
Name: docassemble.LAWVNameChangeClinic
Version: 1.0.7
Summary: A docassemble extension.
Home-page: https://docassemble.org
Author: System Administrator
Author-email: dhenry@lawv.net
License: The MIT License (MIT)
License-File: LICENSE
Requires-Dist: docassemble.LAWVCommon>=1.0.13
Dynamic: author
Dynamic: author-email
Dynamic: description
Dynamic: description-content-type
Dynamic: home-page
Dynamic: license
Dynamic: license-file
Dynamic: requires-dist
Dynamic: summary
